benanalysis-4.0.26.dist-info/METADATA
benanalysis-4.0.26.dist-info/RECORD
benanalysis-4.0.26.dist-info/top_level.txt
benanalysis-4.0.26.dist-info/WHEEL
benanalysis/io.pyi
benanalysis/physics.pyi
benanalysis/fitting.pyi
benanalysis/_benpy_core.cpython-311-x86_64-linux-gnu.so
benanalysis/utils.pyi
benanalysis/__init__.py
benanalysis/curves.pyi
benanalysis/__init__.pyi
benanalysis/radiometry.pyi
benanalysis/chromaticity.pyi
benanalysis/monochromator/__init__.py
benanalysis/monochromator/__init__.pyi
benanalysis/monochromator/slit_function.pyi
benanalysis/colorimetry/__init__.py
benanalysis/colorimetry/data.pyi
benanalysis/colorimetry/__init__.pyi
