Metadata-Version: 2.2
Name: benanalysis
Version: 4.0.26
Summary: Bentham Spectral Analysis and Calibration Utilities Library
Home-page: https://github.com/BenthamInstruments/BenAnalysis
Author: Bentham Instruments Ltd
Author-email: support@bentham.com
Requires-Dist: numpy
Dynamic: author
Dynamic: author-email
Dynamic: description
Dynamic: home-page
Dynamic: requires-dist
Dynamic: summary
